rockmapper/__init__.py
rockmapper/__main__.py
rockmapper/gui_main.py
rockmapper/rock_mapper.py
rockmapper/rock_mapper_tryShadowModel.py
rockmapper/utils.py
rockmapper/version.py
rockmapper-1.0.0a9.dist-info/METADATA
rockmapper-1.0.0a9.dist-info/WHEEL
rockmapper-1.0.0a9.dist-info/top_level.txt
rockmapper-1.0.0a9.dist-info/RECORD
