Metadata-Version: 2.4
Name: rockmapper
Version: 1.0.0a9
Summary: Interface for predicting and mapping benthic habitat (substrates) from any side-scan sonar mosaic.
Author: Cameron Bodine, Wyatt Wolfenkoehler
Author-email: bodine.cs@gmail.email
Project-URL: Issues, https://github.com/PINGEcosystem/RockMapper/issues
Project-URL: GitHub, https://github.com/PINGEcosystem/RockMapper
Keywords: pingmapper,sonar,ecology,remotesensing,sidescan,sidescan-sonar,aquatic,humminbird,lowrance,gis,oceanography,limnology
Classifier: Development Status :: 2 - Pre-Alpha
Classifier: Programming Language :: Python :: 3
Classifier: License :: OSI Approved :: MIT License
Classifier: Operating System :: OS Independent
Classifier: Topic :: Scientific/Engineering
Classifier: Topic :: Scientific/Engineering :: Visualization
Classifier: Topic :: Scientific/Engineering :: Oceanography
Classifier: Topic :: Scientific/Engineering :: GIS
Classifier: Topic :: Scientific/Engineering :: Hydrology
Requires-Python: <3.13
Requires-Dist: pinginstaller
Requires-Dist: pingwizard
Dynamic: author
Dynamic: author-email
Dynamic: classifier
Dynamic: description
Dynamic: description-content-type
Dynamic: keywords
Dynamic: project-url
Dynamic: requires-dist
Dynamic: requires-python
Dynamic: summary
